{
  "bullets": [
    "Core anchors: Nikola Jokic, Jalen Johnson, Jayson Tatum",
    "Leverage plays: Scottie Barnes, Brandon Ingram",
    "Value targets: Sandro Mamukelashvili, Jamal Shead",
    "Fade candidates: Pacome Dadiet, Malevy Leons"
  ],
  "recommendation": "5 core plays anchored at $8,500\u2013$12,000. 3 value plays averaging 5.2 pts/$1K. 5 leverage plays at 0\u20130% ownership.",
  "core_plays": [
    {
      "player_name": "Nikola Jokic",
      "salary": 12000,
      "proj": 62.465,
      "ownership": 0.0,
      "edge": 0.6168288558191026,
      "value": 5.205416666666667,
      "risk_score": 35.8,
      "proj_minutes": 36.1,
      "sim90th": 84.565,
      "ceil": 80.0,
      "sim_leverage": 91.02
    },
    {
      "player_name": "Jalen Johnson",
      "salary": 10500,
      "proj": 50.315,
      "ownership": 13.68,
      "edge": 0.5711298229575612,
      "value": 4.791904761904762,
      "risk_score": 31.8,
      "proj_minutes": 35.7,
      "sim90th": 68.44500000000001,
      "ceil": 63.62,
      "sim_leverage": 14.06
    },
    {
      "player_name": "Jayson Tatum",
      "salary": 8500,
      "proj": 41.435,
      "ownership": 29.71,
      "edge": 0.5207900007966869,
      "value": 4.874705882352941,
      "risk_score": 31.8,
      "proj_minutes": 37.1,
      "sim90th": 58.385,
      "ceil": 54.0,
      "sim_leverage": 2.34
    },
    {
      "player_name": "Jaylen Brown",
      "salary": 8800,
      "proj": 43.035,
      "ownership": 19.41,
      "edge": 0.5105026696342586,
      "value": 4.8903409090909085,
      "risk_score": 34.0,
      "proj_minutes": 32.6,
      "sim90th": 60.695,
      "ceil": 54.16,
      "sim_leverage": 7.03
    },
    {
      "player_name": "Jamal Murray",
      "salary": 8600,
      "proj": 40.745,
      "ownership": 0.0,
      "edge": 0.49839074735509836,
      "value": 4.737790697674418,
      "risk_score": 31.8,
      "proj_minutes": 35.1,
      "sim90th": 57.695,
      "ceil": 53.04,
      "sim_leverage": 85.55
    }
  ],
  "leverage_plays": [
    {
      "player_name": "Scottie Barnes",
      "salary": 8200,
      "proj": 36.245,
      "ownership": 0.0,
      "edge": 0.4730243525454844,
      "value": 4.420121951219512,
      "risk_score": 31.8,
      "proj_minutes": 33.7,
      "sim90th": 51.085,
      "ceil": 47.51,
      "sim_leverage": 80.08
    },
    {
      "player_name": "Brandon Ingram",
      "salary": 7900,
      "proj": 38.044999999999995,
      "ownership": 0.0,
      "edge": 0.42548833494066896,
      "value": 4.815822784810126,
      "risk_score": 31.8,
      "proj_minutes": 33.6,
      "sim90th": 53.885,
      "ceil": 47.79,
      "sim_leverage": 80.86
    },
    {
      "player_name": "Immanuel Quickley",
      "salary": 6700,
      "proj": 33.675,
      "ownership": 0.0,
      "edge": 0.4205734046423716,
      "value": 5.026119402985074,
      "risk_score": 31.8,
      "proj_minutes": 32.2,
      "sim90th": 49.085,
      "ceil": 44.3,
      "sim_leverage": 78.52
    },
    {
      "player_name": "Tobias Harris",
      "salary": 6300,
      "proj": 23.515,
      "ownership": 0.44,
      "edge": 0.41478508786054996,
      "value": 3.7325396825396826,
      "risk_score": 31.8,
      "proj_minutes": 31.0,
      "sim90th": 37.655,
      "ceil": 31.7,
      "sim_leverage": 17.97
    },
    {
      "player_name": "Ziaire Williams",
      "salary": 4000,
      "proj": 18.545,
      "ownership": 0.27,
      "edge": 0.41431464482540126,
      "value": 4.63625,
      "risk_score": 31.8,
      "proj_minutes": 24.0,
      "sim90th": 27.985,
      "ceil": 20.5,
      "sim_leverage": 1.95
    }
  ],
  "value_plays": [
    {
      "player_name": "Sandro Mamukelashvili",
      "salary": 3300,
      "proj": 17.325000000000003,
      "ownership": 0.0,
      "edge": 0.3466547064106857,
      "value": 5.250000000000001,
      "risk_score": 31.8,
      "proj_minutes": 23.8,
      "sim90th": 26.975,
      "ceil": 22.64,
      "sim_leverage": 30.86
    },
    {
      "player_name": "Jamal Shead",
      "salary": 3400,
      "proj": 17.685,
      "ownership": 0.0,
      "edge": 0.29716057369754245,
      "value": 5.201470588235294,
      "risk_score": 37.4,
      "proj_minutes": 21.0,
      "sim90th": 27.845,
      "ceil": 21.24,
      "sim_leverage": 27.73
    },
    {
      "player_name": "Ja'Kobe Walter",
      "salary": 3100,
      "proj": 15.815000000000001,
      "ownership": 0.0,
      "edge": 0.29581408158994127,
      "value": 5.101612903225806,
      "risk_score": 31.8,
      "proj_minutes": 21.3,
      "sim90th": 24.415,
      "ceil": 18.68,
      "sim_leverage": 22.27
    }
  ],
  "fade_candidates": [
    {
      "player_name": "Pacome Dadiet",
      "salary": 3000,
      "proj": 1.635,
      "ownership": 0.05,
      "edge": 0.20423098131604878,
      "value": 0.545,
      "risk_score": 52.2,
      "proj_minutes": 2.8,
      "sim90th": 2.9349999999999996,
      "ceil": 2.65,
      "sim_leverage": -14.84
    },
    {
      "player_name": "Malevy Leons",
      "salary": 3300,
      "proj": 5.105,
      "ownership": 0.44,
      "edge": 0.22260090709177688,
      "value": 1.546969696969697,
      "risk_score": 100.0,
      "proj_minutes": 3.5,
      "sim90th": 8.485,
      "ceil": 8.96,
      "sim_leverage": -28.91
    },
    {
      "player_name": "E.J. Liddell",
      "salary": 3900,
      "proj": 5.875,
      "ownership": 0.34,
      "edge": 0.22967640642246262,
      "value": 1.5064102564102564,
      "risk_score": 57.5,
      "proj_minutes": 4.9,
      "sim90th": 10.405000000000001,
      "ceil": 7.81,
      "sim_leverage": -21.88
    },
    {
      "player_name": "Ochai Agbaji",
      "salary": 3200,
      "proj": 17.555,
      "ownership": 16.86,
      "edge": 0.2817745825822741,
      "value": 5.4859374999999995,
      "risk_score": 69.1,
      "proj_minutes": 13.2,
      "sim90th": 26.535,
      "ceil": 19.49,
      "sim_leverage": -53.91
    },
    {
      "player_name": "Drake Powell",
      "salary": 3300,
      "proj": 13.235,
      "ownership": 0.77,
      "edge": 0.29204526381841267,
      "value": 4.010606060606061,
      "risk_score": 72.2,
      "proj_minutes": 17.4,
      "sim90th": 20.315,
      "ceil": 17.85,
      "sim_leverage": -22.66
    }
  ],
  "signals_df_path": "signals.parquet"
}