{
  "computed_at": "2026-03-09T02:21:31.833661+00:00",
  "n_slates": 9,
  "n_player_slates": 1661,
  "ratios": {
    "lt5k": 0.601,
    "5_65k": 0.3988,
    "65_8k": 0.3361,
    "8_10k": 0.2685,
    "10k_plus": 0.28
  },
  "brackets": {
    "lt5k": {
      "n": 915,
      "learned_ratio": 0.601,
      "clamped_ratio": 0.601,
      "static_ratio": 1.04,
      "delta_pct": -42.2,
      "using": "learned",
      "value": 0.601,
      "mean_proj": 15.7,
      "residual_std": 9.4
    },
    "5_65k": {
      "n": 359,
      "learned_ratio": 0.3988,
      "clamped_ratio": 0.3988,
      "static_ratio": 0.64,
      "delta_pct": -37.7,
      "using": "learned",
      "value": 0.3988,
      "mean_proj": 25.5,
      "residual_std": 10.2
    },
    "65_8k": {
      "n": 203,
      "learned_ratio": 0.3361,
      "clamped_ratio": 0.3361,
      "static_ratio": 0.44,
      "delta_pct": -23.6,
      "using": "learned",
      "value": 0.3361,
      "mean_proj": 32.8,
      "residual_std": 11.0
    },
    "8_10k": {
      "n": 145,
      "learned_ratio": 0.2685,
      "clamped_ratio": 0.2685,
      "static_ratio": 0.35,
      "delta_pct": -23.3,
      "using": "learned",
      "value": 0.2685,
      "mean_proj": 40.4,
      "residual_std": 10.8
    },
    "10k_plus": {
      "n": 39,
      "learned_ratio": 0.28,
      "clamped_ratio": 0.28,
      "static_ratio": 0.3,
      "delta_pct": -6.7,
      "using": "learned",
      "value": 0.28,
      "mean_proj": 48.6,
      "residual_std": 13.6
    }
  }
}