{
  "computed_at": "2026-03-16T10:15:26.567806+00:00",
  "n_slates": 24,
  "signal_stats": {
    "high_leverage": {
      "total_flagged": 1872,
      "total_hit": 609,
      "raw_hit_rate": 0.325,
      "weighted_hit_rate": 0.337,
      "n_slates_active": 21
    },
    "salary_value": {
      "total_flagged": 122,
      "total_hit": 41,
      "raw_hit_rate": 0.336,
      "weighted_hit_rate": 0.324,
      "n_slates_active": 22
    }
  },
  "weights": {
    "high_leverage": 0.51,
    "salary_value": 0.49
  }
}